grank/__init__.py
grank/core.py
grank/analy/__init__.py
grank/analy/core.py
grank/libs/__init__.py
grank/libs/helpers.py
grank/libs/query.py
grank/script/__init__.py
grank/script/activity.py
grank/script/crawler.py
grank/script/social.py
tests/__init__.py
tests/test_basic.py
tests/test_helpers.py
ljjGrank-1.0.4.dist-info/LICENSE
ljjGrank-1.0.4.dist-info/METADATA
ljjGrank-1.0.4.dist-info/WHEEL
ljjGrank-1.0.4.dist-info/entry_points.txt
ljjGrank-1.0.4.dist-info/top_level.txt
ljjGrank-1.0.4.dist-info/RECORD
