Metadata-Version: 2.1
Name: ljjGrank
Version: 1.0.4
Summary: A Github Project Rank Command Line Tool
Home-page: https://github.com/LCTT/Grank
Author: LCTT
Author-email: 2200201796@qq.com
License: GPLv3
Platform: UNKNOWN
Classifier: Programming Language :: Python :: 3
Requires-Python: >=3.4
Requires-Dist: click
Requires-Dist: requests
Requires-Dist: pandas
Requires-Dist: numpy
Requires-Dist: matplotlib
